unifi_protect_rclone/__init__.py
unifi_protect_rclone/cli.py
unifi_protect_rclone/downloader.py
unifi_protect_rclone/downloader_experimental.py
unifi_protect_rclone/event_listener.py
unifi_protect_rclone/missing_event_checker.py
unifi_protect_rclone/notifications.py
unifi_protect_rclone/purge.py
unifi_protect_rclone/unifi_protect_rclone_core.py
unifi_protect_rclone/uploader.py
unifi_protect_rclone/utils.py
unifi_protect_rclone-0.12.3.dist-info/LICENSE
unifi_protect_rclone-0.12.3.dist-info/METADATA
unifi_protect_rclone-0.12.3.dist-info/WHEEL
unifi_protect_rclone-0.12.3.dist-info/entry_points.txt
unifi_protect_rclone-0.12.3.dist-info/RECORD
