Metadata-Version: 2.1
Name: unifi_protect_rclone
Version: 0.12.3
Summary: Python tool to backup unifi event clips in realtime.
Home-page: https://github.com/Calimerorulez/unifi-protect-rclone
License: MIT
Author: Pat
Author-email: calimerorulez@gmail.com
Requires-Python: >=3.10.0,<4.0
Classifier: Development Status :: 5 - Production/Stable
Classifier: Intended Audience :: Information Technology
Classifier: License :: OSI Approved :: MIT License
Classifier: Natural Language :: English
Classifier: Programming Language :: Python :: 3
Classifier: Programming Language :: Python :: 3.10
Classifier: Programming Language :: Python :: 3.11
Classifier: Programming Language :: Python :: 3.12
Classifier: Programming Language :: Python :: 3.13
Requires-Dist: aiolimiter (>=1.1.0,<2.0.0)
Requires-Dist: aiorun (>=2023.7.2,<2024.0.0)
Requires-Dist: aiosqlite (>=0.17.0,<0.18.0)
Requires-Dist: apprise (>=1.5.0,<2.0.0)
Requires-Dist: async-lru (>=2.0.4,<3.0.0)
Requires-Dist: click (==8.0.1)
Requires-Dist: expiring-dict (>=1.1.0,<2.0.0)
Requires-Dist: python-dateutil (>=2.8.2,<3.0.0)
Requires-Dist: uiprotect (>=6.7.0,<7.0.0)
